README.txt
setup.cfg
setup.py
ganna/__init__.py
ganna.egg-info/PKG-INFO
ganna.egg-info/SOURCES.txt
ganna.egg-info/dependency_links.txt
ganna.egg-info/entry_points.txt
ganna.egg-info/not-zip-safe
ganna.egg-info/top_level.txt