Metadata-Version: 1.0
Name: ganna
Version: 0.1dev
Summary: Python_course
Home-page: UNKNOWN
Author: andrea ganna
Author-email: andrea.ganna@gmail.com
License: UNKNOWN
Platform: UNKNOWN
